thoth/solver/__init__.py
thoth/solver/_typing.py
thoth/solver/cli.py
thoth/solver/exceptions.py
thoth/solver/py.typed
thoth/solver/python/__init__.py
thoth/solver/python/base.py
thoth/solver/python/instrument.py
thoth/solver/python/python.py
thoth/solver/python/python_solver.py
thoth_solver-1.6.0.dist-info/METADATA
thoth_solver-1.6.0.dist-info/RECORD
thoth_solver-1.6.0.dist-info/WHEEL
thoth_solver-1.6.0.dist-info/entry_points.txt
thoth_solver-1.6.0.dist-info/top_level.txt
