Metadata-Version: 2.1
Name: thoth-solver
Version: 1.6.0
Summary: Tool and library for discovering package dependencies in PyPI world
Home-page: https://github.com/thoth-station/solver
Author: Fridolin Pokorny
Author-email: fridolin@redhat.com
Maintainer: Fridolin Pokorny
Maintainer-email: fridolin@redhat.com
License: GPLv3+
Keywords: python dependency pypi dependencies tool library
Platform: UNKNOWN
Classifier: Development Status :: 4 - Beta
Classifier: Programming Language :: Python :: 3
Classifier: Programming Language :: Python :: 3.4
Classifier: Programming Language :: Python :: 3.5
Classifier: Environment :: Console
Classifier: Intended Audience :: Developers
Classifier: License :: OSI Approved :: Apache Software License
Classifier: Operating System :: OS Independent
Classifier: Programming Language :: Python :: Implementation :: CPython
Classifier: Programming Language :: Python :: Implementation :: PyPy
Requires-Dist: attr
Requires-Dist: autopep8
Requires-Dist: click
Requires-Dist: packaging
Requires-Dist: pipdeptree
Requires-Dist: requests
Requires-Dist: thoth-analyzer
Requires-Dist: thoth-common
Requires-Dist: thoth-python
Requires-Dist: virtualenv
Requires-Dist: importlib-metadata; python_version < "3.8"
